filtergenius/__init__.py
filtergenius/filter.py
filtergenius-0.2.0.dist-info/METADATA
filtergenius-0.2.0.dist-info/WHEEL
filtergenius-0.2.0.dist-info/top_level.txt
filtergenius-0.2.0.dist-info/RECORD
