Metadata-Version: 2.4
Name: filtergenius
Version: 0.2.0
Summary: FilterGenius: Smart filters to detect email, phone, emoji, numeric types, and strings.
Author-email: sanjeev <sanjeevsanju929@gmail.com>
License: MIT
Project-URL: Homepage, https://github.com/sanjeev929/filtergenius
Keywords: filter,email,phone,emoji,string,number
Requires-Python: >=3.7
